{
  "type": "VStack",
  "properties": {
    "spacing": 10.0,
    "alignment": "center",
    "padding": "default"
  },
  "children": [
    {
      "type": "Text",
      "properties": {
        "text": "Gauge Variants"
      }
    },
    {
      "type": "Gauge",
      "properties": {
        "value": 65,
        "style": "accessoryCircular",
        "range": {
          "min": 0.0,
          "max": 100.0
        }
      }
    },
    {
      "type": "Gauge",
      "properties": {
        "value": 0.4,
        "title": "Level",
        "style": "accessoryLinear"
      }
    }
  ]
}
